{
    "id": "79d68a3fd37fd1d3cd45b5b2f2d33549",
    "name": "Clearbit",
    "description": null,
    "auth": null,
    "events": null,
    "variables": [],
    "order": [],
    "folders_order": [],
    "folders": [],
    "requests": [
        {
            "id": "83478f23ca1cf2119908cae56a95ad4d",
            "name": "Find Contacts - Job Title",
            "url": "httpsdiscovery.clearbit.com\/v1\/companies\/search",
            "description": "TODO: Add Description",
            "data": [],
            "dataMode": "raw",
            "headerData": null,
            "method": "get",
            "pathVariableData": [],
            "queryParams": [
                {
                    "key": "domain",
                    "description": "",
                    "value": "",
                    "equals": true,
                    "enabled": true
                },
                {
                    "key": "title",
                    "description": "",
                    "value": "",
                    "equals": true,
                    "enabled": true
                },
                {
                    "key": "email",
                    "description": "",
                    "value": "",
                    "equals": true,
                    "enabled": true
                }
            ],
            "auth": null,
            "events": null,
            "folder": null,
            "protocolProfileBehavior": {
                "disableBodyPruning": true
            },
            "responses": [],
            "currentHelper": null,
            "helperAttributes": null,
            "collectionId": "79d68a3fd37fd1d3cd45b5b2f2d33549",
            "rawModeData": ""
        },
        {
            "id": "2809e915c271cb4b77406186c5a161b0",
            "name": "Domain Lookup",
            "url": "httpsdiscovery.clearbit.com\/v1\/companies\/v2\/companies\/find",
            "description": "TODO: Add Description",
            "data": [],
            "dataMode": "raw",
            "headerData": null,
            "method": "get",
            "pathVariableData": [],
            "queryParams": [
                {
                    "key": "domain",
                    "description": "",
                    "value": "",
                    "equals": true,
                    "enabled": true
                }
            ],
            "auth": null,
            "events": null,
            "folder": null,
            "protocolProfileBehavior": {
                "disableBodyPruning": true
            },
            "responses": [],
            "currentHelper": null,
            "helperAttributes": null,
            "collectionId": "79d68a3fd37fd1d3cd45b5b2f2d33549",
            "rawModeData": ""
        },
        {
            "id": "3631d7f0639588871754a5f20697d9b8",
            "name": "Find Company by IP Address",
            "url": "httpsdiscovery.clearbit.com\/v1\/companies\/find",
            "description": "TODO: Add Description",
            "data": [],
            "dataMode": "raw",
            "headerData": null,
            "method": "get",
            "pathVariableData": [],
            "queryParams": [
                {
                    "key": "ip",
                    "description": "",
                    "value": "",
                    "equals": true,
                    "enabled": true
                }
            ],
            "auth": null,
            "events": null,
            "folder": null,
            "protocolProfileBehavior": {
                "disableBodyPruning": true
            },
            "responses": [],
            "currentHelper": null,
            "helperAttributes": null,
            "collectionId": "79d68a3fd37fd1d3cd45b5b2f2d33549",
            "rawModeData": ""
        },
        {
            "id": "c338752289cae6c832492e1374d4c962",
            "name": "Company Name to Domain",
            "url": "httpsdiscovery.clearbit.com\/v1\/companies\/v1\/domains\/find",
            "description": "TODO: Add Description",
            "data": [],
            "dataMode": "raw",
            "headerData": null,
            "method": "get",
            "pathVariableData": [],
            "queryParams": [
                {
                    "key": "name",
                    "description": "",
                    "value": "",
                    "equals": true,
                    "enabled": true
                }
            ],
            "auth": null,
            "events": null,
            "folder": null,
            "protocolProfileBehavior": {
                "disableBodyPruning": true
            },
            "responses": [],
            "currentHelper": null,
            "helperAttributes": null,
            "collectionId": "79d68a3fd37fd1d3cd45b5b2f2d33549",
            "rawModeData": ""
        },
        {
            "id": "62a325461da06561c2a1acd15fe3723c",
            "name": "By Name",
            "url": "httpsdiscovery.clearbit.com\/v1\/companies\/entities",
            "description": "TODO: Add Description",
            "data": [],
            "dataMode": "raw",
            "headerData": null,
            "method": "get",
            "pathVariableData": [],
            "queryParams": [
                {
                    "key": "name",
                    "description": "",
                    "value": "",
                    "equals": true,
                    "enabled": true
                }
            ],
            "auth": null,
            "events": null,
            "folder": null,
            "protocolProfileBehavior": {
                "disableBodyPruning": true
            },
            "responses": [],
            "currentHelper": null,
            "helperAttributes": null,
            "collectionId": "79d68a3fd37fd1d3cd45b5b2f2d33549",
            "rawModeData": ""
        }
    ]
}